genshinstats/__init__.py
genshinstats/caching.py
genshinstats/daily.py
genshinstats/errors.py
genshinstats/genshinstats.py
genshinstats/hoyolab.py
genshinstats/map.py
genshinstats/pretty.py
genshinstats/transactions.py
genshinstats/utils.py
genshinstats/wishes.py
genshinstats-1.4.10.1.dist-info/LICENSE
genshinstats-1.4.10.1.dist-info/METADATA
genshinstats-1.4.10.1.dist-info/WHEEL
genshinstats-1.4.10.1.dist-info/top_level.txt
genshinstats-1.4.10.1.dist-info/RECORD
