Metadata-Version: 2.1
Name: genshinstats
Version: 1.4.10.1
Summary: A python library that can get the stats of Genshin Impact players using Mihoyo's API.
Home-page: https://github.com/thesadru/genshinstats
Author: thesadru
Author-email: thesadru@gmail.com
License: MIT
Project-URL: Documentation, https://thesadru.github.io/pdoc/genshinstats/
Project-URL: Issue tracker, https://github.com/thesadru/genshinstats/issues
Keywords: api,wrapper,mihoyo,genshin,genshin-impact
Platform: UNKNOWN
Classifier: Development Status :: 5 - Production/Stable
Classifier: Intended Audience :: Developers
Classifier: License :: OSI Approved :: MIT License
Classifier: Operating System :: OS Independent
Classifier: Programming Language :: Python
Classifier: Topic :: Internet :: WWW/HTTP
Classifier: Topic :: Software Development :: Libraries
Classifier: Topic :: Software Development :: Libraries :: Python Modules
Classifier: Topic :: Utilities
Classifier: Typing :: Typed
Requires-Python: >=3.7
License-File: LICENSE
Requires-Dist: requests
Requires-Dist: browser-cookie3
